protomaps/__init__.py
protomaps-0.0.1.dist-info/LICENSE
protomaps-0.0.1.dist-info/METADATA
protomaps-0.0.1.dist-info/WHEEL
protomaps-0.0.1.dist-info/top_level.txt
protomaps-0.0.1.dist-info/RECORD
