Metadata-Version: 2.1
Name: protomaps
Version: 0.0.1
Summary: Interact with Protomaps API
Home-page: https://protomaps.com/docs/python
Author: Protomaps
Author-email: hi@protomaps.com
License: UNKNOWN
Platform: UNKNOWN
Classifier: Programming Language :: Python :: 3
Classifier: License :: OSI Approved :: BSD License
Classifier: Operating System :: OS Independent
